examples/__init__.py
examples/example_run.py
universalrag/__init__.py
universalrag/embedder.py
universalrag/pipeline.py
universalrag/retriever.py
universalrag/extractors/__init__.py
universalrag/extractors/audio.py
universalrag/extractors/docx.py
universalrag/extractors/image.py
universalrag/extractors/pdf.py
universalrag/extractors/url.py
universalrag/extractors/video.py
universalrag/models/__init__.py
universalrag/models/groq_gen.py
universalrag/models/hf_gen.py
universalrag/models/openai_gen.py
universalrag/utility/__init__.py
universalrag/utility/summarizer.py
universalrag-0.1.0.dist-info/METADATA
universalrag-0.1.0.dist-info/WHEEL
universalrag-0.1.0.dist-info/top_level.txt
universalrag-0.1.0.dist-info/RECORD
