Metadata-Version: 2.4
Name: universalrag
Version: 0.1.0
Summary: A plug-and-play multimodal Retrieval-Augmented Generation (RAG) framework
Home-page: https://github.com/vigyat13/universalrag_pypi
Author: Vigyat Singh
Author-email: vigyatsingh2004@gmail.com
Classifier: Programming Language :: Python :: 3
Classifier: Operating System :: OS Independent
Classifier: License :: OSI Approved :: MIT License
Requires-Python: >=3.8
Requires-Dist: openai
Requires-Dist: faiss-cpu
Requires-Dist: sentence-transformers
Requires-Dist: PyPDF2
Requires-Dist: python-docx
Requires-Dist: pytesseract
Requires-Dist: transformers
Requires-Dist: moviepy
Requires-Dist: whisper
Requires-Dist: requests
Requires-Dist: bs4
Requires-Dist: python-dotenv
Requires-Dist: torchaudio
Requires-Dist: easyocr
Requires-Dist: torch
Requires-Dist: Pillow
Requires-Dist: python-bidi
Requires-Dist: tiktoken
Requires-Dist: huggingface_hub
Requires-Dist: groq
Dynamic: author
Dynamic: author-email
Dynamic: classifier
Dynamic: description
Dynamic: description-content-type
Dynamic: home-page
Dynamic: requires-dist
Dynamic: requires-python
Dynamic: summary
